__init__.py
exechain/__init__.py
exechain/base.py
exechain/exechain.py
exechain/exeptions.py
exechain/filesystem.py
exechain/git.py
exechain/internal.py
exechain/network.py
exechain/pkgmanager.py
exechain/shell.py
exechain/cli/exechainmake.py
exechain-0.0.5.dist-info/LICENSE.md
exechain-0.0.5.dist-info/METADATA
exechain-0.0.5.dist-info/WHEEL
exechain-0.0.5.dist-info/entry_points.txt
exechain-0.0.5.dist-info/top_level.txt
exechain-0.0.5.dist-info/RECORD
